sciRED/__init__.py
sciRED/ensembleFCA.py
sciRED/glm.py
sciRED/metrics.py
sciRED/permutation.py
sciRED/rotations.py
sciRED/examples/__init__.py
sciRED/examples/ex_preprocess.py
sciRED/examples/ex_visualize.py
sciRED/examples/simulation.py
sciRED/utils/__init__.py
sciRED/utils/corr.py
sciRED/utils/preprocess.py
sciRED/utils/visualize.py
sciRED-1.2.1.dist-info/LICENSE
sciRED-1.2.1.dist-info/METADATA
sciRED-1.2.1.dist-info/WHEEL
sciRED-1.2.1.dist-info/top_level.txt
sciRED-1.2.1.dist-info/RECORD
